setup.py
soundloader/__init__.py
soundloader/exceptions.py
soundloader/utils.py
soundloader.egg-info/PKG-INFO
soundloader.egg-info/SOURCES.txt
soundloader.egg-info/dependency_links.txt
soundloader.egg-info/requires.txt
soundloader.egg-info/top_level.txt