Metadata-Version: 1.0
Name: soundloader
Version: 0.1
Summary: Downloads songs, albums or playlists through soundcloud link
Home-page: https://github.com/An0nimia/soundloader
Author: An0nimia
Author-email: An0nimia@protonmail.com
License: CC BY-NC-SA 4.0
Platform: UNKNOWN
